{
  "last_updated": "2026-07-15T16:38:55+00:00",
  "barris": [
    {
      "barri_codi": "0632",
      "barri_nom": "el Camp d'en Grassot i Gràcia Nova",
      "stations_count": 4,
      "stations_active": 4,
      "capacity_total": 105,
      "docks_available_total": 78,
      "bikes_mechanical": 0,
      "bikes_ebike": 0,
      "bikes_total": 0,
      "pct_bikes": 0.0,
      "pct_docks_free": 74.29,
      "pct_mechanical": 0.0,
      "pct_ebike": 0.0,
      "stations_zero_ebike": 4,
      "stations_zero_mechanical": 4,
      "stations_zero_any": 4,
      "superficie_ha": 0.0,
      "bikes_out_of_service": 25,
      "pct_bikes_out_of_service": 23.81,
      "docks_disabled_total": 0
    },
    {
      "barri_codi": "0851",
      "barri_nom": "Verdun",
      "stations_count": 2,
      "stations_active": 2,
      "capacity_total": 44,
      "docks_available_total": 39,
      "bikes_mechanical": 0,
      "bikes_ebike": 0,
      "bikes_total": 0,
      "pct_bikes": 0.0,
      "pct_docks_free": 88.64,
      "pct_mechanical": 0.0,
      "pct_ebike": 0.0,
      "stations_zero_ebike": 2,
      "stations_zero_mechanical": 2,
      "stations_zero_any": 2,
      "superficie_ha": 0.0,
      "bikes_out_of_service": 5,
      "pct_bikes_out_of_service": 11.36,
      "docks_disabled_total": 0
    },
    {
      "barri_codi": "0850",
      "barri_nom": "les Roquetes",
      "stations_count": 1,
      "stations_active": 1,
      "capacity_total": 18,
      "docks_available_total": 16,
      "bikes_mechanical": 0,
      "bikes_ebike": 0,
      "bikes_total": 0,
      "pct_bikes": 0.0,
      "pct_docks_free": 88.89,
      "pct_mechanical": 0.0,
      "pct_ebike": 0.0,
      "stations_zero_ebike": 1,
      "stations_zero_mechanical": 1,
      "stations_zero_any": 1,
      "superficie_ha": 0.0,
      "bikes_out_of_service": 2,
      "pct_bikes_out_of_service": 11.11,
      "docks_disabled_total": 0
    },
    {
      "barri_codi": "0849",
      "barri_nom": "Canyelles",
      "stations_count": 1,
      "stations_active": 1,
      "capacity_total": 24,
      "docks_available_total": 24,
      "bikes_mechanical": 0,
      "bikes_ebike": 0,
      "bikes_total": 0,
      "pct_bikes": 0.0,
      "pct_docks_free": 100.0,
      "pct_mechanical": 0.0,
      "pct_ebike": 0.0,
      "stations_zero_ebike": 1,
      "stations_zero_mechanical": 1,
      "stations_zero_any": 1,
      "superficie_ha": 0.0,
      "bikes_out_of_service": 0,
      "pct_bikes_out_of_service": 0.0,
      "docks_disabled_total": 0
    },
    {
      "barri_codi": "0630",
      "barri_nom": "la Salut",
      "stations_count": 2,
      "stations_active": 2,
      "capacity_total": 57,
      "docks_available_total": 50,
      "bikes_mechanical": 0,
      "bikes_ebike": 2,
      "bikes_total": 1,
      "pct_bikes": 1.75,
      "pct_docks_free": 87.72,
      "pct_mechanical": 0.0,
      "pct_ebike": 3.51,
      "stations_zero_ebike": 1,
      "stations_zero_mechanical": 2,
      "stations_zero_any": 1,
      "superficie_ha": 0.0,
      "bikes_out_of_service": 3,
      "pct_bikes_out_of_service": 5.26,
      "docks_disabled_total": 2
    },
    {
      "barri_codi": "0527",
      "barri_nom": "el Putxet i el Farró",
      "stations_count": 2,
      "stations_active": 2,
      "capacity_total": 43,
      "docks_available_total": 34,
      "bikes_mechanical": 0,
      "bikes_ebike": 3,
      "bikes_total": 1,
      "pct_bikes": 2.33,
      "pct_docks_free": 79.07,
      "pct_mechanical": 0.0,
      "pct_ebike": 6.98,
      "stations_zero_ebike": 1,
      "stations_zero_mechanical": 2,
      "stations_zero_any": 1,
      "superficie_ha": 0.0,
      "bikes_out_of_service": 5,
      "pct_bikes_out_of_service": 11.63,
      "docks_disabled_total": 0
    },
    {
      "barri_codi": "0737",
      "barri_nom": "el Carmel",
      "stations_count": 3,
      "stations_active": 3,
      "capacity_total": 77,
      "docks_available_total": 68,
      "bikes_mechanical": 2,
      "bikes_ebike": 0,
      "bikes_total": 2,
      "pct_bikes": 2.6,
      "pct_docks_free": 88.31,
      "pct_mechanical": 2.6,
      "pct_ebike": 0.0,
      "stations_zero_ebike": 3,
      "stations_zero_mechanical": 2,
      "stations_zero_any": 2,
      "superficie_ha": 0.0,
      "bikes_out_of_service": 5,
      "pct_bikes_out_of_service": 6.49,
      "docks_disabled_total": 2
    },
    {
      "barri_codi": "0421",
      "barri_nom": "Pedralbes",
      "stations_count": 9,
      "stations_active": 9,
      "capacity_total": 304,
      "docks_available_total": 267,
      "bikes_mechanical": 3,
      "bikes_ebike": 7,
      "bikes_total": 10,
      "pct_bikes": 3.29,
      "pct_docks_free": 87.83,
      "pct_mechanical": 0.99,
      "pct_ebike": 2.3,
      "stations_zero_ebike": 5,
      "stations_zero_mechanical": 7,
      "stations_zero_any": 3,
      "superficie_ha": 0.0,
      "bikes_out_of_service": 25,
      "pct_bikes_out_of_service": 8.22,
      "docks_disabled_total": 2
    },
    {
      "barri_codi": "0848",
      "barri_nom": "la Guineueta",
      "stations_count": 5,
      "stations_active": 5,
      "capacity_total": 120,
      "docks_available_total": 111,
      "bikes_mechanical": 0,
      "bikes_ebike": 5,
      "bikes_total": 4,
      "pct_bikes": 3.33,
      "pct_docks_free": 92.5,
      "pct_mechanical": 0.0,
      "pct_ebike": 4.17,
      "stations_zero_ebike": 2,
      "stations_zero_mechanical": 5,
      "stations_zero_any": 2,
      "superficie_ha": 0.0,
      "bikes_out_of_service": 3,
      "pct_bikes_out_of_service": 2.5,
      "docks_disabled_total": 0
    },
    {
      "barri_codi": "0736",
      "barri_nom": "la Font d'en Fargues",
      "stations_count": 3,
      "stations_active": 3,
      "capacity_total": 77,
      "docks_available_total": 71,
      "bikes_mechanical": 0,
      "bikes_ebike": 3,
      "bikes_total": 3,
      "pct_bikes": 3.9,
      "pct_docks_free": 92.21,
      "pct_mechanical": 0.0,
      "pct_ebike": 3.9,
      "stations_zero_ebike": 0,
      "stations_zero_mechanical": 3,
      "stations_zero_any": 0,
      "superficie_ha": 0.0,
      "bikes_out_of_service": 2,
      "pct_bikes_out_of_service": 2.6,
      "docks_disabled_total": 0
    },
    {
      "barri_codi": "0852",
      "barri_nom": "la Prosperitat",
      "stations_count": 5,
      "stations_active": 5,
      "capacity_total": 118,
      "docks_available_total": 103,
      "bikes_mechanical": 1,
      "bikes_ebike": 4,
      "bikes_total": 5,
      "pct_bikes": 4.24,
      "pct_docks_free": 87.29,
      "pct_mechanical": 0.85,
      "pct_ebike": 3.39,
      "stations_zero_ebike": 2,
      "stations_zero_mechanical": 4,
      "stations_zero_any": 2,
      "superficie_ha": 0.0,
      "bikes_out_of_service": 8,
      "pct_bikes_out_of_service": 6.78,
      "docks_disabled_total": 0
    },
    {
      "barri_codi": "0733",
      "barri_nom": "el Baix Guinardó",
      "stations_count": 8,
      "stations_active": 8,
      "capacity_total": 226,
      "docks_available_total": 190,
      "bikes_mechanical": 1,
      "bikes_ebike": 9,
      "bikes_total": 10,
      "pct_bikes": 4.42,
      "pct_docks_free": 84.07,
      "pct_mechanical": 0.44,
      "pct_ebike": 3.98,
      "stations_zero_ebike": 3,
      "stations_zero_mechanical": 7,
      "stations_zero_any": 2,
      "superficie_ha": 0.0,
      "bikes_out_of_service": 24,
      "pct_bikes_out_of_service": 10.62,
      "docks_disabled_total": 0
    },
    {
      "barri_codi": "0628",
      "barri_nom": "Vallcarca i els Penitents",
      "stations_count": 5,
      "stations_active": 5,
      "capacity_total": 119,
      "docks_available_total": 95,
      "bikes_mechanical": 1,
      "bikes_ebike": 6,
      "bikes_total": 6,
      "pct_bikes": 5.04,
      "pct_docks_free": 79.83,
      "pct_mechanical": 0.84,
      "pct_ebike": 5.04,
      "stations_zero_ebike": 2,
      "stations_zero_mechanical": 4,
      "stations_zero_any": 1,
      "superficie_ha": 0.0,
      "bikes_out_of_service": 13,
      "pct_bikes_out_of_service": 10.92,
      "docks_disabled_total": 2
    },
    {
      "barri_codi": "0853",
      "barri_nom": "la Trinitat Nova",
      "stations_count": 2,
      "stations_active": 2,
      "capacity_total": 52,
      "docks_available_total": 47,
      "bikes_mechanical": 0,
      "bikes_ebike": 3,
      "bikes_total": 3,
      "pct_bikes": 5.77,
      "pct_docks_free": 90.38,
      "pct_mechanical": 0.0,
      "pct_ebike": 5.77,
      "stations_zero_ebike": 0,
      "stations_zero_mechanical": 2,
      "stations_zero_any": 0,
      "superficie_ha": 0.0,
      "bikes_out_of_service": 1,
      "pct_bikes_out_of_service": 1.92,
      "docks_disabled_total": 1
    },
    {
      "barri_codi": "0523",
      "barri_nom": "Sarrià",
      "stations_count": 8,
      "stations_active": 8,
      "capacity_total": 217,
      "docks_available_total": 175,
      "bikes_mechanical": 5,
      "bikes_ebike": 10,
      "bikes_total": 13,
      "pct_bikes": 5.99,
      "pct_docks_free": 80.65,
      "pct_mechanical": 2.3,
      "pct_ebike": 4.61,
      "stations_zero_ebike": 3,
      "stations_zero_mechanical": 7,
      "stations_zero_any": 2,
      "superficie_ha": 0.0,
      "bikes_out_of_service": 23,
      "pct_bikes_out_of_service": 10.6,
      "docks_disabled_total": 1
    },
    {
      "barri_codi": "0739",
      "barri_nom": "Sant Genís dels Agudells",
      "stations_count": 2,
      "stations_active": 2,
      "capacity_total": 59,
      "docks_available_total": 54,
      "bikes_mechanical": 3,
      "bikes_ebike": 1,
      "bikes_total": 4,
      "pct_bikes": 6.78,
      "pct_docks_free": 91.53,
      "pct_mechanical": 5.08,
      "pct_ebike": 1.69,
      "stations_zero_ebike": 1,
      "stations_zero_mechanical": 1,
      "stations_zero_any": 1,
      "superficie_ha": 0.0,
      "bikes_out_of_service": 1,
      "pct_bikes_out_of_service": 1.69,
      "docks_disabled_total": 0
    },
    {
      "barri_codi": "0525",
      "barri_nom": "Sant Gervasi - la Bonanova",
      "stations_count": 6,
      "stations_active": 6,
      "capacity_total": 162,
      "docks_available_total": 139,
      "bikes_mechanical": 9,
      "bikes_ebike": 2,
      "bikes_total": 11,
      "pct_bikes": 6.79,
      "pct_docks_free": 85.8,
      "pct_mechanical": 5.56,
      "pct_ebike": 1.23,
      "stations_zero_ebike": 4,
      "stations_zero_mechanical": 4,
      "stations_zero_any": 3,
      "superficie_ha": 0.0,
      "bikes_out_of_service": 9,
      "pct_bikes_out_of_service": 5.56,
      "docks_disabled_total": 2
    },
    {
      "barri_codi": "0206",
      "barri_nom": "la Sagrada Família",
      "stations_count": 16,
      "stations_active": 16,
      "capacity_total": 405,
      "docks_available_total": 307,
      "bikes_mechanical": 16,
      "bikes_ebike": 17,
      "bikes_total": 30,
      "pct_bikes": 7.41,
      "pct_docks_free": 75.8,
      "pct_mechanical": 3.95,
      "pct_ebike": 4.2,
      "stations_zero_ebike": 5,
      "stations_zero_mechanical": 12,
      "stations_zero_any": 5,
      "superficie_ha": 0.0,
      "bikes_out_of_service": 66,
      "pct_bikes_out_of_service": 16.3,
      "docks_disabled_total": 1
    },
    {
      "barri_codi": "0420",
      "barri_nom": "la Maternitat i Sant Ramon",
      "stations_count": 11,
      "stations_active": 11,
      "capacity_total": 302,
      "docks_available_total": 251,
      "bikes_mechanical": 8,
      "bikes_ebike": 15,
      "bikes_total": 23,
      "pct_bikes": 7.62,
      "pct_docks_free": 83.11,
      "pct_mechanical": 2.65,
      "pct_ebike": 4.97,
      "stations_zero_ebike": 6,
      "stations_zero_mechanical": 7,
      "stations_zero_any": 5,
      "superficie_ha": 0.0,
      "bikes_out_of_service": 27,
      "pct_bikes_out_of_service": 8.94,
      "docks_disabled_total": 3
    },
    {
      "barri_codi": "0526",
      "barri_nom": "Sant Gervasi - Galvany",
      "stations_count": 15,
      "stations_active": 15,
      "capacity_total": 386,
      "docks_available_total": 277,
      "bikes_mechanical": 20,
      "bikes_ebike": 16,
      "bikes_total": 32,
      "pct_bikes": 8.29,
      "pct_docks_free": 71.76,
      "pct_mechanical": 5.18,
      "pct_ebike": 4.15,
      "stations_zero_ebike": 7,
      "stations_zero_mechanical": 11,
      "stations_zero_any": 5,
      "superficie_ha": 0.0,
      "bikes_out_of_service": 71,
      "pct_bikes_out_of_service": 18.39,
      "docks_disabled_total": 0
    },
    {
      "barri_codi": "0631",
      "barri_nom": "la Vila de Gràcia",
      "stations_count": 14,
      "stations_active": 14,
      "capacity_total": 362,
      "docks_available_total": 240,
      "bikes_mechanical": 4,
      "bikes_ebike": 33,
      "bikes_total": 30,
      "pct_bikes": 8.29,
      "pct_docks_free": 66.3,
      "pct_mechanical": 1.1,
      "pct_ebike": 9.12,
      "stations_zero_ebike": 2,
      "stations_zero_mechanical": 10,
      "stations_zero_any": 2,
      "superficie_ha": 0.0,
      "bikes_out_of_service": 80,
      "pct_bikes_out_of_service": 22.1,
      "docks_disabled_total": 3
    },
    {
      "barri_codi": "0419",
      "barri_nom": "les Corts",
      "stations_count": 17,
      "stations_active": 17,
      "capacity_total": 457,
      "docks_available_total": 349,
      "bikes_mechanical": 32,
      "bikes_ebike": 9,
      "bikes_total": 40,
      "pct_bikes": 8.75,
      "pct_docks_free": 76.37,
      "pct_mechanical": 7.0,
      "pct_ebike": 1.97,
      "stations_zero_ebike": 10,
      "stations_zero_mechanical": 11,
      "stations_zero_any": 6,
      "superficie_ha": 0.0,
      "bikes_out_of_service": 65,
      "pct_bikes_out_of_service": 14.22,
      "docks_disabled_total": 1
    },
    {
      "barri_codi": "0735",
      "barri_nom": "el Guinardó",
      "stations_count": 8,
      "stations_active": 8,
      "capacity_total": 211,
      "docks_available_total": 150,
      "bikes_mechanical": 16,
      "bikes_ebike": 4,
      "bikes_total": 19,
      "pct_bikes": 9.0,
      "pct_docks_free": 71.09,
      "pct_mechanical": 7.58,
      "pct_ebike": 1.9,
      "stations_zero_ebike": 6,
      "stations_zero_mechanical": 6,
      "stations_zero_any": 4,
      "superficie_ha": 0.0,
      "bikes_out_of_service": 38,
      "pct_bikes_out_of_service": 18.01,
      "docks_disabled_total": 0
    },
    {
      "barri_codi": "0962",
      "barri_nom": "el Congrés i els Indians",
      "stations_count": 5,
      "stations_active": 5,
      "capacity_total": 133,
      "docks_available_total": 109,
      "bikes_mechanical": 5,
      "bikes_ebike": 7,
      "bikes_total": 12,
      "pct_bikes": 9.02,
      "pct_docks_free": 81.95,
      "pct_mechanical": 3.76,
      "pct_ebike": 5.26,
      "stations_zero_ebike": 1,
      "stations_zero_mechanical": 2,
      "stations_zero_any": 0,
      "superficie_ha": 0.0,
      "bikes_out_of_service": 11,
      "pct_bikes_out_of_service": 8.27,
      "docks_disabled_total": 0
    },
    {
      "barri_codi": "0961",
      "barri_nom": "la Sagrera",
      "stations_count": 7,
      "stations_active": 7,
      "capacity_total": 205,
      "docks_available_total": 150,
      "bikes_mechanical": 13,
      "bikes_ebike": 11,
      "bikes_total": 22,
      "pct_bikes": 10.73,
      "pct_docks_free": 73.17,
      "pct_mechanical": 6.34,
      "pct_ebike": 5.37,
      "stations_zero_ebike": 1,
      "stations_zero_mechanical": 1,
      "stations_zero_any": 0,
      "superficie_ha": 0.0,
      "bikes_out_of_service": 32,
      "pct_bikes_out_of_service": 15.61,
      "docks_disabled_total": 0
    },
    {
      "barri_codi": "0207",
      "barri_nom": "la Dreta de l'Eixample",
      "stations_count": 41,
      "stations_active": 41,
      "capacity_total": 1037,
      "docks_available_total": 754,
      "bikes_mechanical": 86,
      "bikes_ebike": 33,
      "bikes_total": 116,
      "pct_bikes": 11.19,
      "pct_docks_free": 72.71,
      "pct_mechanical": 8.29,
      "pct_ebike": 3.18,
      "stations_zero_ebike": 20,
      "stations_zero_mechanical": 15,
      "stations_zero_any": 11,
      "superficie_ha": 0.0,
      "bikes_out_of_service": 148,
      "pct_bikes_out_of_service": 14.27,
      "docks_disabled_total": 13
    },
    {
      "barri_codi": "0209",
      "barri_nom": "la Nova Esquerra de l'Eixample",
      "stations_count": 18,
      "stations_active": 18,
      "capacity_total": 490,
      "docks_available_total": 336,
      "bikes_mechanical": 35,
      "bikes_ebike": 33,
      "bikes_total": 63,
      "pct_bikes": 12.86,
      "pct_docks_free": 68.57,
      "pct_mechanical": 7.14,
      "pct_ebike": 6.73,
      "stations_zero_ebike": 4,
      "stations_zero_mechanical": 6,
      "stations_zero_any": 2,
      "superficie_ha": 0.0,
      "bikes_out_of_service": 80,
      "pct_bikes_out_of_service": 16.33,
      "docks_disabled_total": 1
    },
    {
      "barri_codi": "0524",
      "barri_nom": "les Tres Torres",
      "stations_count": 8,
      "stations_active": 8,
      "capacity_total": 220,
      "docks_available_total": 173,
      "bikes_mechanical": 25,
      "bikes_ebike": 4,
      "bikes_total": 29,
      "pct_bikes": 13.18,
      "pct_docks_free": 78.64,
      "pct_mechanical": 11.36,
      "pct_ebike": 1.82,
      "stations_zero_ebike": 4,
      "stations_zero_mechanical": 5,
      "stations_zero_any": 3,
      "superficie_ha": 0.0,
      "bikes_out_of_service": 19,
      "pct_bikes_out_of_service": 8.64,
      "docks_disabled_total": 0
    },
    {
      "barri_codi": "0846",
      "barri_nom": "el Turó de la Peira",
      "stations_count": 2,
      "stations_active": 2,
      "capacity_total": 45,
      "docks_available_total": 27,
      "bikes_mechanical": 2,
      "bikes_ebike": 4,
      "bikes_total": 6,
      "pct_bikes": 13.33,
      "pct_docks_free": 60.0,
      "pct_mechanical": 4.44,
      "pct_ebike": 8.89,
      "stations_zero_ebike": 0,
      "stations_zero_mechanical": 1,
      "stations_zero_any": 0,
      "superficie_ha": 0.0,
      "bikes_out_of_service": 12,
      "pct_bikes_out_of_service": 26.67,
      "docks_disabled_total": 0
    },
    {
      "barri_codi": "1064",
      "barri_nom": "el Camp de l'Arpa del Clot",
      "stations_count": 5,
      "stations_active": 5,
      "capacity_total": 131,
      "docks_available_total": 85,
      "bikes_mechanical": 8,
      "bikes_ebike": 12,
      "bikes_total": 18,
      "pct_bikes": 13.74,
      "pct_docks_free": 64.89,
      "pct_mechanical": 6.11,
      "pct_ebike": 9.16,
      "stations_zero_ebike": 2,
      "stations_zero_mechanical": 1,
      "stations_zero_any": 1,
      "superficie_ha": 0.0,
      "bikes_out_of_service": 26,
      "pct_bikes_out_of_service": 19.85,
      "docks_disabled_total": 0
    },
    {
      "barri_codi": "0743",
      "barri_nom": "Horta",
      "stations_count": 9,
      "stations_active": 9,
      "capacity_total": 232,
      "docks_available_total": 191,
      "bikes_mechanical": 28,
      "bikes_ebike": 5,
      "bikes_total": 33,
      "pct_bikes": 14.22,
      "pct_docks_free": 82.33,
      "pct_mechanical": 12.07,
      "pct_ebike": 2.16,
      "stations_zero_ebike": 4,
      "stations_zero_mechanical": 3,
      "stations_zero_any": 0,
      "superficie_ha": 0.0,
      "bikes_out_of_service": 7,
      "pct_bikes_out_of_service": 3.02,
      "docks_disabled_total": 1
    },
    {
      "barri_codi": "0844",
      "barri_nom": "Vilapicina i la Torre Llobeta",
      "stations_count": 4,
      "stations_active": 4,
      "capacity_total": 101,
      "docks_available_total": 75,
      "bikes_mechanical": 5,
      "bikes_ebike": 10,
      "bikes_total": 15,
      "pct_bikes": 14.85,
      "pct_docks_free": 74.26,
      "pct_mechanical": 4.95,
      "pct_ebike": 9.9,
      "stations_zero_ebike": 0,
      "stations_zero_mechanical": 2,
      "stations_zero_any": 0,
      "superficie_ha": 0.0,
      "bikes_out_of_service": 11,
      "pct_bikes_out_of_service": 10.89,
      "docks_disabled_total": 0
    },
    {
      "barri_codi": "0312",
      "barri_nom": "la Marina del Prat Vermell",
      "stations_count": 2,
      "stations_active": 2,
      "capacity_total": 79,
      "docks_available_total": 62,
      "bikes_mechanical": 3,
      "bikes_ebike": 10,
      "bikes_total": 13,
      "pct_bikes": 16.46,
      "pct_docks_free": 78.48,
      "pct_mechanical": 3.8,
      "pct_ebike": 12.66,
      "stations_zero_ebike": 1,
      "stations_zero_mechanical": 0,
      "stations_zero_any": 0,
      "superficie_ha": 0.0,
      "bikes_out_of_service": 2,
      "pct_bikes_out_of_service": 2.53,
      "docks_disabled_total": 2
    },
    {
      "barri_codi": "0741",
      "barri_nom": "la Vall d'Hebron",
      "stations_count": 6,
      "stations_active": 6,
      "capacity_total": 175,
      "docks_available_total": 139,
      "bikes_mechanical": 28,
      "bikes_ebike": 2,
      "bikes_total": 30,
      "pct_bikes": 17.14,
      "pct_docks_free": 79.43,
      "pct_mechanical": 16.0,
      "pct_ebike": 1.14,
      "stations_zero_ebike": 4,
      "stations_zero_mechanical": 1,
      "stations_zero_any": 0,
      "superficie_ha": 0.0,
      "bikes_out_of_service": 6,
      "pct_bikes_out_of_service": 3.43,
      "docks_disabled_total": 0
    },
    {
      "barri_codi": "0315",
      "barri_nom": "Hostafrancs",
      "stations_count": 7,
      "stations_active": 7,
      "capacity_total": 191,
      "docks_available_total": 129,
      "bikes_mechanical": 22,
      "bikes_ebike": 13,
      "bikes_total": 35,
      "pct_bikes": 18.32,
      "pct_docks_free": 67.54,
      "pct_mechanical": 11.52,
      "pct_ebike": 6.81,
      "stations_zero_ebike": 2,
      "stations_zero_mechanical": 1,
      "stations_zero_any": 0,
      "superficie_ha": 0.0,
      "bikes_out_of_service": 23,
      "pct_bikes_out_of_service": 12.04,
      "docks_disabled_total": 1
    },
    {
      "barri_codi": "0208",
      "barri_nom": "l'Antiga Esquerra de l'Eixample",
      "stations_count": 14,
      "stations_active": 13,
      "capacity_total": 338,
      "docks_available_total": 216,
      "bikes_mechanical": 35,
      "bikes_ebike": 28,
      "bikes_total": 62,
      "pct_bikes": 18.34,
      "pct_docks_free": 63.91,
      "pct_mechanical": 10.36,
      "pct_ebike": 8.28,
      "stations_zero_ebike": 5,
      "stations_zero_mechanical": 7,
      "stations_zero_any": 3,
      "superficie_ha": 0.0,
      "bikes_out_of_service": 57,
      "pct_bikes_out_of_service": 16.86,
      "docks_disabled_total": 3
    },
    {
      "barri_codi": "0963",
      "barri_nom": "Navas",
      "stations_count": 4,
      "stations_active": 4,
      "capacity_total": 116,
      "docks_available_total": 81,
      "bikes_mechanical": 16,
      "bikes_ebike": 6,
      "bikes_total": 22,
      "pct_bikes": 18.97,
      "pct_docks_free": 69.83,
      "pct_mechanical": 13.79,
      "pct_ebike": 5.17,
      "stations_zero_ebike": 2,
      "stations_zero_mechanical": 0,
      "stations_zero_any": 0,
      "superficie_ha": 0.0,
      "bikes_out_of_service": 12,
      "pct_bikes_out_of_service": 10.34,
      "docks_disabled_total": 1
    },
    {
      "barri_codi": "0318",
      "barri_nom": "Sants",
      "stations_count": 12,
      "stations_active": 12,
      "capacity_total": 277,
      "docks_available_total": 168,
      "bikes_mechanical": 37,
      "bikes_ebike": 19,
      "bikes_total": 55,
      "pct_bikes": 19.86,
      "pct_docks_free": 60.65,
      "pct_mechanical": 13.36,
      "pct_ebike": 6.86,
      "stations_zero_ebike": 2,
      "stations_zero_mechanical": 4,
      "stations_zero_any": 1,
      "superficie_ha": 0.0,
      "bikes_out_of_service": 51,
      "pct_bikes_out_of_service": 18.41,
      "docks_disabled_total": 1
    },
    {
      "barri_codi": "0960",
      "barri_nom": "Sant Andreu",
      "stations_count": 16,
      "stations_active": 16,
      "capacity_total": 414,
      "docks_available_total": 296,
      "bikes_mechanical": 48,
      "bikes_ebike": 35,
      "bikes_total": 83,
      "pct_bikes": 20.05,
      "pct_docks_free": 71.5,
      "pct_mechanical": 11.59,
      "pct_ebike": 8.45,
      "stations_zero_ebike": 6,
      "stations_zero_mechanical": 5,
      "stations_zero_any": 2,
      "superficie_ha": 0.0,
      "bikes_out_of_service": 30,
      "pct_bikes_out_of_service": 7.25,
      "docks_disabled_total": 2
    },
    {
      "barri_codi": "0313",
      "barri_nom": "la Marina de Port",
      "stations_count": 11,
      "stations_active": 11,
      "capacity_total": 316,
      "docks_available_total": 217,
      "bikes_mechanical": 52,
      "bikes_ebike": 16,
      "bikes_total": 67,
      "pct_bikes": 21.2,
      "pct_docks_free": 68.67,
      "pct_mechanical": 16.46,
      "pct_ebike": 5.06,
      "stations_zero_ebike": 3,
      "stations_zero_mechanical": 1,
      "stations_zero_any": 0,
      "superficie_ha": 0.0,
      "bikes_out_of_service": 31,
      "pct_bikes_out_of_service": 9.81,
      "docks_disabled_total": 1
    },
    {
      "barri_codi": "0845",
      "barri_nom": "Porta",
      "stations_count": 6,
      "stations_active": 6,
      "capacity_total": 159,
      "docks_available_total": 107,
      "bikes_mechanical": 17,
      "bikes_ebike": 21,
      "bikes_total": 38,
      "pct_bikes": 23.9,
      "pct_docks_free": 67.3,
      "pct_mechanical": 10.69,
      "pct_ebike": 13.21,
      "stations_zero_ebike": 1,
      "stations_zero_mechanical": 4,
      "stations_zero_any": 1,
      "superficie_ha": 0.0,
      "bikes_out_of_service": 13,
      "pct_bikes_out_of_service": 8.18,
      "docks_disabled_total": 1
    },
    {
      "barri_codi": "0311",
      "barri_nom": "el Poble-sec",
      "stations_count": 12,
      "stations_active": 12,
      "capacity_total": 324,
      "docks_available_total": 208,
      "bikes_mechanical": 46,
      "bikes_ebike": 37,
      "bikes_total": 83,
      "pct_bikes": 25.62,
      "pct_docks_free": 64.2,
      "pct_mechanical": 14.2,
      "pct_ebike": 11.42,
      "stations_zero_ebike": 4,
      "stations_zero_mechanical": 5,
      "stations_zero_any": 1,
      "superficie_ha": 0.0,
      "bikes_out_of_service": 30,
      "pct_bikes_out_of_service": 9.26,
      "docks_disabled_total": 3
    },
    {
      "barri_codi": "0205",
      "barri_nom": "el Fort Pienc",
      "stations_count": 13,
      "stations_active": 13,
      "capacity_total": 409,
      "docks_available_total": 252,
      "bikes_mechanical": 83,
      "bikes_ebike": 26,
      "bikes_total": 107,
      "pct_bikes": 26.16,
      "pct_docks_free": 61.61,
      "pct_mechanical": 20.29,
      "pct_ebike": 6.36,
      "stations_zero_ebike": 4,
      "stations_zero_mechanical": 1,
      "stations_zero_any": 1,
      "superficie_ha": 0.0,
      "bikes_out_of_service": 42,
      "pct_bikes_out_of_service": 10.27,
      "docks_disabled_total": 3
    },
    {
      "barri_codi": "0316",
      "barri_nom": "la Bordeta",
      "stations_count": 6,
      "stations_active": 6,
      "capacity_total": 175,
      "docks_available_total": 106,
      "bikes_mechanical": 36,
      "bikes_ebike": 13,
      "bikes_total": 49,
      "pct_bikes": 28.0,
      "pct_docks_free": 60.57,
      "pct_mechanical": 20.57,
      "pct_ebike": 7.43,
      "stations_zero_ebike": 0,
      "stations_zero_mechanical": 1,
      "stations_zero_any": 0,
      "superficie_ha": 0.0,
      "bikes_out_of_service": 20,
      "pct_bikes_out_of_service": 11.43,
      "docks_disabled_total": 0
    },
    {
      "barri_codi": "0210",
      "barri_nom": "Sant Antoni",
      "stations_count": 17,
      "stations_active": 17,
      "capacity_total": 460,
      "docks_available_total": 250,
      "bikes_mechanical": 101,
      "bikes_ebike": 36,
      "bikes_total": 135,
      "pct_bikes": 29.35,
      "pct_docks_free": 54.35,
      "pct_mechanical": 21.96,
      "pct_ebike": 7.83,
      "stations_zero_ebike": 3,
      "stations_zero_mechanical": 1,
      "stations_zero_any": 0,
      "superficie_ha": 0.0,
      "bikes_out_of_service": 67,
      "pct_bikes_out_of_service": 14.57,
      "docks_disabled_total": 2
    },
    {
      "barri_codi": "1066",
      "barri_nom": "el Parc i la Llacuna del Poblenou",
      "stations_count": 12,
      "stations_active": 12,
      "capacity_total": 351,
      "docks_available_total": 164,
      "bikes_mechanical": 103,
      "bikes_ebike": 20,
      "bikes_total": 117,
      "pct_bikes": 33.33,
      "pct_docks_free": 46.72,
      "pct_mechanical": 29.34,
      "pct_ebike": 5.7,
      "stations_zero_ebike": 5,
      "stations_zero_mechanical": 0,
      "stations_zero_any": 0,
      "superficie_ha": 0.0,
      "bikes_out_of_service": 55,
      "pct_bikes_out_of_service": 15.67,
      "docks_disabled_total": 2
    },
    {
      "barri_codi": "0317",
      "barri_nom": "Sants - Badal",
      "stations_count": 5,
      "stations_active": 5,
      "capacity_total": 141,
      "docks_available_total": 71,
      "bikes_mechanical": 24,
      "bikes_ebike": 23,
      "bikes_total": 47,
      "pct_bikes": 33.33,
      "pct_docks_free": 50.35,
      "pct_mechanical": 17.02,
      "pct_ebike": 16.31,
      "stations_zero_ebike": 0,
      "stations_zero_mechanical": 0,
      "stations_zero_any": 0,
      "superficie_ha": 0.0,
      "bikes_out_of_service": 22,
      "pct_bikes_out_of_service": 15.6,
      "docks_disabled_total": 1
    },
    {
      "barri_codi": "0314",
      "barri_nom": "la Font de la Guatlla",
      "stations_count": 2,
      "stations_active": 2,
      "capacity_total": 36,
      "docks_available_total": 13,
      "bikes_mechanical": 9,
      "bikes_ebike": 4,
      "bikes_total": 12,
      "pct_bikes": 33.33,
      "pct_docks_free": 36.11,
      "pct_mechanical": 25.0,
      "pct_ebike": 11.11,
      "stations_zero_ebike": 0,
      "stations_zero_mechanical": 0,
      "stations_zero_any": 0,
      "superficie_ha": 0.0,
      "bikes_out_of_service": 8,
      "pct_bikes_out_of_service": 22.22,
      "docks_disabled_total": 1
    },
    {
      "barri_codi": "0957",
      "barri_nom": "la Trinitat Vella",
      "stations_count": 5,
      "stations_active": 5,
      "capacity_total": 122,
      "docks_available_total": 72,
      "bikes_mechanical": 27,
      "bikes_ebike": 14,
      "bikes_total": 41,
      "pct_bikes": 33.61,
      "pct_docks_free": 59.02,
      "pct_mechanical": 22.13,
      "pct_ebike": 11.48,
      "stations_zero_ebike": 0,
      "stations_zero_mechanical": 0,
      "stations_zero_any": 0,
      "superficie_ha": 0.0,
      "bikes_out_of_service": 4,
      "pct_bikes_out_of_service": 3.28,
      "docks_disabled_total": 5
    },
    {
      "barri_codi": "1073",
      "barri_nom": "la Verneda i la Pau",
      "stations_count": 5,
      "stations_active": 5,
      "capacity_total": 141,
      "docks_available_total": 74,
      "bikes_mechanical": 21,
      "bikes_ebike": 27,
      "bikes_total": 48,
      "pct_bikes": 34.04,
      "pct_docks_free": 52.48,
      "pct_mechanical": 14.89,
      "pct_ebike": 19.15,
      "stations_zero_ebike": 0,
      "stations_zero_mechanical": 0,
      "stations_zero_any": 0,
      "superficie_ha": 0.0,
      "bikes_out_of_service": 17,
      "pct_bikes_out_of_service": 12.06,
      "docks_disabled_total": 0
    },
    {
      "barri_codi": "0101",
      "barri_nom": "el Raval",
      "stations_count": 17,
      "stations_active": 16,
      "capacity_total": 435,
      "docks_available_total": 226,
      "bikes_mechanical": 136,
      "bikes_ebike": 16,
      "bikes_total": 152,
      "pct_bikes": 34.94,
      "pct_docks_free": 51.95,
      "pct_mechanical": 31.26,
      "pct_ebike": 3.68,
      "stations_zero_ebike": 7,
      "stations_zero_mechanical": 1,
      "stations_zero_any": 1,
      "superficie_ha": 0.0,
      "bikes_out_of_service": 54,
      "pct_bikes_out_of_service": 12.41,
      "docks_disabled_total": 1
    },
    {
      "barri_codi": "1065",
      "barri_nom": "el Clot",
      "stations_count": 6,
      "stations_active": 6,
      "capacity_total": 147,
      "docks_available_total": 61,
      "bikes_mechanical": 44,
      "bikes_ebike": 14,
      "bikes_total": 54,
      "pct_bikes": 36.73,
      "pct_docks_free": 41.5,
      "pct_mechanical": 29.93,
      "pct_ebike": 9.52,
      "stations_zero_ebike": 2,
      "stations_zero_mechanical": 1,
      "stations_zero_any": 0,
      "superficie_ha": 0.0,
      "bikes_out_of_service": 27,
      "pct_bikes_out_of_service": 18.37,
      "docks_disabled_total": 0
    },
    {
      "barri_codi": "0958",
      "barri_nom": "Baró de Viver",
      "stations_count": 2,
      "stations_active": 2,
      "capacity_total": 51,
      "docks_available_total": 29,
      "bikes_mechanical": 16,
      "bikes_ebike": 4,
      "bikes_total": 20,
      "pct_bikes": 39.22,
      "pct_docks_free": 56.86,
      "pct_mechanical": 31.37,
      "pct_ebike": 7.84,
      "stations_zero_ebike": 0,
      "stations_zero_mechanical": 0,
      "stations_zero_any": 0,
      "superficie_ha": 0.0,
      "bikes_out_of_service": 1,
      "pct_bikes_out_of_service": 1.96,
      "docks_disabled_total": 1
    },
    {
      "barri_codi": "0103",
      "barri_nom": "la Barceloneta",
      "stations_count": 15,
      "stations_active": 15,
      "capacity_total": 436,
      "docks_available_total": 217,
      "bikes_mechanical": 162,
      "bikes_ebike": 17,
      "bikes_total": 175,
      "pct_bikes": 40.14,
      "pct_docks_free": 49.77,
      "pct_mechanical": 37.16,
      "pct_ebike": 3.9,
      "stations_zero_ebike": 7,
      "stations_zero_mechanical": 1,
      "stations_zero_any": 1,
      "superficie_ha": 0.0,
      "bikes_out_of_service": 37,
      "pct_bikes_out_of_service": 8.49,
      "docks_disabled_total": 2
    },
    {
      "barri_codi": "1067",
      "barri_nom": "la Vila Olímpica del Poblenou",
      "stations_count": 15,
      "stations_active": 15,
      "capacity_total": 548,
      "docks_available_total": 276,
      "bikes_mechanical": 206,
      "bikes_ebike": 26,
      "bikes_total": 229,
      "pct_bikes": 41.79,
      "pct_docks_free": 50.36,
      "pct_mechanical": 37.59,
      "pct_ebike": 4.74,
      "stations_zero_ebike": 7,
      "stations_zero_mechanical": 1,
      "stations_zero_any": 1,
      "superficie_ha": 0.0,
      "bikes_out_of_service": 33,
      "pct_bikes_out_of_service": 6.02,
      "docks_disabled_total": 4
    },
    {
      "barri_codi": "0104",
      "barri_nom": "Sant Pere, Santa Caterina i la Ribera",
      "stations_count": 10,
      "stations_active": 10,
      "capacity_total": 247,
      "docks_available_total": 106,
      "bikes_mechanical": 100,
      "bikes_ebike": 14,
      "bikes_total": 111,
      "pct_bikes": 44.94,
      "pct_docks_free": 42.91,
      "pct_mechanical": 40.49,
      "pct_ebike": 5.67,
      "stations_zero_ebike": 2,
      "stations_zero_mechanical": 0,
      "stations_zero_any": 0,
      "superficie_ha": 0.0,
      "bikes_out_of_service": 24,
      "pct_bikes_out_of_service": 9.72,
      "docks_disabled_total": 1
    },
    {
      "barri_codi": "1071",
      "barri_nom": "Provençals del Poblenou",
      "stations_count": 10,
      "stations_active": 10,
      "capacity_total": 267,
      "docks_available_total": 107,
      "bikes_mechanical": 121,
      "bikes_ebike": 8,
      "bikes_total": 129,
      "pct_bikes": 48.31,
      "pct_docks_free": 40.07,
      "pct_mechanical": 45.32,
      "pct_ebike": 3.0,
      "stations_zero_ebike": 6,
      "stations_zero_mechanical": 0,
      "stations_zero_any": 0,
      "superficie_ha": 0.0,
      "bikes_out_of_service": 29,
      "pct_bikes_out_of_service": 10.86,
      "docks_disabled_total": 0
    },
    {
      "barri_codi": "1068",
      "barri_nom": "el Poblenou",
      "stations_count": 17,
      "stations_active": 17,
      "capacity_total": 483,
      "docks_available_total": 148,
      "bikes_mechanical": 219,
      "bikes_ebike": 40,
      "bikes_total": 254,
      "pct_bikes": 52.59,
      "pct_docks_free": 30.64,
      "pct_mechanical": 45.34,
      "pct_ebike": 8.28,
      "stations_zero_ebike": 6,
      "stations_zero_mechanical": 0,
      "stations_zero_any": 0,
      "superficie_ha": 0.0,
      "bikes_out_of_service": 73,
      "pct_bikes_out_of_service": 15.11,
      "docks_disabled_total": 2
    },
    {
      "barri_codi": "0959",
      "barri_nom": "el Bon Pastor",
      "stations_count": 8,
      "stations_active": 8,
      "capacity_total": 202,
      "docks_available_total": 81,
      "bikes_mechanical": 86,
      "bikes_ebike": 24,
      "bikes_total": 109,
      "pct_bikes": 53.96,
      "pct_docks_free": 40.1,
      "pct_mechanical": 42.57,
      "pct_ebike": 11.88,
      "stations_zero_ebike": 1,
      "stations_zero_mechanical": 0,
      "stations_zero_any": 0,
      "superficie_ha": 0.0,
      "bikes_out_of_service": 11,
      "pct_bikes_out_of_service": 5.45,
      "docks_disabled_total": 0
    },
    {
      "barri_codi": "0855",
      "barri_nom": "Ciutat Meridiana",
      "stations_count": 1,
      "stations_active": 1,
      "capacity_total": 20,
      "docks_available_total": 5,
      "bikes_mechanical": 1,
      "bikes_ebike": 10,
      "bikes_total": 11,
      "pct_bikes": 55.0,
      "pct_docks_free": 25.0,
      "pct_mechanical": 5.0,
      "pct_ebike": 50.0,
      "stations_zero_ebike": 0,
      "stations_zero_mechanical": 0,
      "stations_zero_any": 0,
      "superficie_ha": 0.0,
      "bikes_out_of_service": 4,
      "pct_bikes_out_of_service": 20.0,
      "docks_disabled_total": 0
    },
    {
      "barri_codi": "1070",
      "barri_nom": "el Besòs i el Maresme",
      "stations_count": 8,
      "stations_active": 8,
      "capacity_total": 298,
      "docks_available_total": 114,
      "bikes_mechanical": 114,
      "bikes_ebike": 51,
      "bikes_total": 165,
      "pct_bikes": 55.37,
      "pct_docks_free": 38.26,
      "pct_mechanical": 38.26,
      "pct_ebike": 17.11,
      "stations_zero_ebike": 1,
      "stations_zero_mechanical": 0,
      "stations_zero_any": 0,
      "superficie_ha": 0.0,
      "bikes_out_of_service": 18,
      "pct_bikes_out_of_service": 6.04,
      "docks_disabled_total": 0
    },
    {
      "barri_codi": "0102",
      "barri_nom": "el Barri Gòtic",
      "stations_count": 12,
      "stations_active": 12,
      "capacity_total": 322,
      "docks_available_total": 100,
      "bikes_mechanical": 176,
      "bikes_ebike": 10,
      "bikes_total": 186,
      "pct_bikes": 57.76,
      "pct_docks_free": 31.06,
      "pct_mechanical": 54.66,
      "pct_ebike": 3.11,
      "stations_zero_ebike": 6,
      "stations_zero_mechanical": 0,
      "stations_zero_any": 0,
      "superficie_ha": 0.0,
      "bikes_out_of_service": 35,
      "pct_bikes_out_of_service": 10.87,
      "docks_disabled_total": 0
    },
    {
      "barri_codi": "1069",
      "barri_nom": "Diagonal Mar i el Front Marítim del Poblenou",
      "stations_count": 9,
      "stations_active": 9,
      "capacity_total": 242,
      "docks_available_total": 66,
      "bikes_mechanical": 128,
      "bikes_ebike": 26,
      "bikes_total": 153,
      "pct_bikes": 63.22,
      "pct_docks_free": 27.27,
      "pct_mechanical": 52.89,
      "pct_ebike": 10.74,
      "stations_zero_ebike": 3,
      "stations_zero_mechanical": 0,
      "stations_zero_any": 0,
      "superficie_ha": 0.0,
      "bikes_out_of_service": 22,
      "pct_bikes_out_of_service": 9.09,
      "docks_disabled_total": 0
    },
    {
      "barri_codi": "1072",
      "barri_nom": "Sant Martí de Provençals",
      "stations_count": 4,
      "stations_active": 4,
      "capacity_total": 116,
      "docks_available_total": 25,
      "bikes_mechanical": 62,
      "bikes_ebike": 19,
      "bikes_total": 81,
      "pct_bikes": 69.83,
      "pct_docks_free": 21.55,
      "pct_mechanical": 53.45,
      "pct_ebike": 16.38,
      "stations_zero_ebike": 1,
      "stations_zero_mechanical": 0,
      "stations_zero_any": 0,
      "superficie_ha": 0.0,
      "bikes_out_of_service": 10,
      "pct_bikes_out_of_service": 8.62,
      "docks_disabled_total": 0
    }
  ]
}